dpvisu/__init__.py
dpvisu/__main__.py
dpvisu/components/__init__.py
dpvisu/components/abstract_node.py
dpvisu/components/advancement.py
dpvisu/components/call_manager.py
dpvisu/components/cluster.py
dpvisu/components/edge.py
dpvisu/components/function.py
dpvisu/components/function_tag.py
dpvisu/components/node.py
dpvisu/datapack_visualizer.py
dpvisu/main.py
dpvisu-0.8.1.dist-info/entry_points.txt
dpvisu-0.8.1.dist-info/WHEEL
dpvisu-0.8.1.dist-info/METADATA
dpvisu-0.8.1.dist-info/licenses/LICENSE
dpvisu-0.8.1.dist-info/RECORD
