Metadata-Version: 2.1
Name: dpvisu
Version: 0.8.1
Summary: A bodge disguised as a tool that generates call-graphs when let loose on a datapack.
License: GPL-3.0
Author-email: Thaodan <327625-UncleThaodan@users.noreply.gitlab.com>
Requires-Python: >=3.12
Classifier: Development Status :: 4 - Beta
Classifier: Intended Audience :: Developers
Classifier: Operating System :: OS Independent
Requires-Dist: diagrams>=0.21.1
Project-URL: Repository, https://gitlab.com/Thaodan/datapack_visualizer
